{
	"info": {
		"_postman_id": "aaa85f79-9df0-47c0-9094-1706c6e6178b",
		"name": "【文件上传】",
		"schema": "https://schema.getpostman.com/json/collection/v2.1.0/collection.json",
		"_exporter_id": "37834822"
	},
	"item": [
		{
			"name": "【文件上传】【健康检查】",
			"request": {
				"method": "GET",
				"header": [],
				"url": {
					"raw": "http://120.46.208.202:8087/health",
					"protocol": "http",
					"host": [
						"120",
						"46",
						"208",
						"202"
					],
					"port": "8087",
					"path": [
						"health"
					]
				}
			},
			"response": [
				{
					"name": "【文件上传】【健康检查】",
					"originalRequest": {
						"method": "GET",
						"header": [],
						"url": {
							"raw": "http://8.tcp.cpolar.cn:11195/health",
							"protocol": "http",
							"host": [
								"8",
								"tcp",
								"cpolar",
								"cn"
							],
							"port": "11195",
							"path": [
								"health"
							]
						}
					},
					"status": "OK",
					"code": 200,
					"_postman_previewlanguage": "json",
					"header": [
						{
							"key": "Connection",
							"value": "close"
						},
						{
							"key": "Content-Length",
							"value": "15"
						},
						{
							"key": "Content-Type",
							"value": "application/json"
						},
						{
							"key": "Date",
							"value": "Tue, 10 Jun 2025 09:19:35 GMT"
						},
						{
							"key": "Server",
							"value": "uvicorn"
						}
					],
					"cookie": [],
					"body": "{\n    \"status\": \"ok\"\n}"
				}
			]
		},
		{
			"name": "【文件上传】【获取支持的文件格式】",
			"request": {
				"method": "GET",
				"header": [],
				"url": {
					"raw": "http://120.46.208.202:8087/get_supported_file_types",
					"protocol": "http",
					"host": [
						"120",
						"46",
						"208",
						"202"
					],
					"port": "8087",
					"path": [
						"get_supported_file_types"
					]
				}
			},
			"response": [
				{
					"name": "【文件上传】【获取支持的文件格式】",
					"originalRequest": {
						"method": "GET",
						"header": [],
						"url": {
							"raw": "http://8.tcp.cpolar.cn:11195/get_supported_file_types",
							"protocol": "http",
							"host": [
								"8",
								"tcp",
								"cpolar",
								"cn"
							],
							"port": "11195",
							"path": [
								"get_supported_file_types"
							]
						}
					},
					"status": "OK",
					"code": 200,
					"_postman_previewlanguage": "json",
					"header": [
						{
							"key": "Connection",
							"value": "close"
						},
						{
							"key": "Content-Length",
							"value": "277"
						},
						{
							"key": "Content-Type",
							"value": "application/json"
						},
						{
							"key": "Date",
							"value": "Tue, 10 Jun 2025 09:20:00 GMT"
						},
						{
							"key": "Server",
							"value": "uvicorn"
						}
					],
					"cookie": [],
					"body": "{\n    \"status\": \"ok\",\n    \"message\": \"Supported file types\",\n    \"data\": {\n        \"supported_file_types\": [\n            \".doc\",\n            \".docx\",\n            \".ppt\",\n            \".pptx\",\n            \".xls\",\n            \".xlsx\",\n            \".odt\",\n            \".ods\",\n            \".odp\",\n            \".txt\",\n            \".rtf\",\n            \".jpg\",\n            \".jpeg\",\n            \".png\",\n            \".tiff\",\n            \".tif\",\n            \".bmp\",\n            \".html\",\n            \".htm\",\n            \".md\",\n            \".csv\",\n            \".tsv\",\n            \".xml\",\n            \".py\",\n            \".ipynb\",\n            \".js\",\n            \".json\"\n        ]\n    }\n}"
				}
			]
		},
		{
			"name": "【文件上传】【获取文件公网链接】",
			"request": {
				"method": "POST",
				"header": [],
				"body": {
					"mode": "formdata",
					"formdata": [
						{
							"key": "user_id",
							"value": "xxxx",
							"description": "请先创建用户再上传",
							"type": "text"
						},
						{
							"key": "upload_file",
							"type": "file",
							"src": "/C:/Users/meidi/Desktop/【排版结果】国际商务谈判.docx"
						}
					]
				},
				"url": {
					"raw": "http://120.46.208.202:8087/upload_minio",
					"protocol": "http",
					"host": [
						"120",
						"46",
						"208",
						"202"
					],
					"port": "8087",
					"path": [
						"upload_minio"
					]
				}
			},
			"response": [
				{
					"name": "【文件上传】【获取文件公网链接】",
					"originalRequest": {
						"method": "POST",
						"header": [],
						"body": {
							"mode": "formdata",
							"formdata": [
								{
									"key": "user_id",
									"value": "xxxx",
									"type": "text"
								},
								{
									"key": "upload_file",
									"type": "file",
									"src": "/C:/Users/meidi/Desktop/embedding_service -9030.py"
								}
							]
						},
						"url": {
							"raw": "http://8.tcp.cpolar.cn:11195/upload_minio",
							"protocol": "http",
							"host": [
								"8",
								"tcp",
								"cpolar",
								"cn"
							],
							"port": "11195",
							"path": [
								"upload_minio"
							]
						}
					},
					"status": "OK",
					"code": 200,
					"_postman_previewlanguage": "json",
					"header": [
						{
							"key": "Connection",
							"value": "close"
						},
						{
							"key": "Content-Length",
							"value": "422"
						},
						{
							"key": "Content-Type",
							"value": "application/json"
						},
						{
							"key": "Date",
							"value": "Tue, 10 Jun 2025 09:20:09 GMT"
						},
						{
							"key": "Server",
							"value": "uvicorn"
						}
					],
					"cookie": [],
					"body": "{\n    \"status\": \"success\",\n    \"message\": \"File uploaded successfully\",\n    \"data\": {\n        \"file_id\": \"c7c70308-672c-4d81-a5b0-71dcb7323634\",\n        \"filename\": \"embedding_service -9030.py\",\n        \"object_path\": \"xxxx/default_file_space/c7c70308-672c-4d81-a5b0-71dcb7323634/embedding_service -9030.py\",\n        \"public_url\": \"http://1.tcp.cpolar.cn:21729/publicfiles/xxxx/default_file_space/c7c70308-672c-4d81-a5b0-71dcb7323634/embedding_service -9030.py\",\n        \"file_size\": 4680\n    }\n}"
				}
			]
		},
		{
			"name": "【文件上传】【存文件到知识库】",
			"request": {
				"method": "POST",
				"header": [],
				"body": {
					"mode": "formdata",
					"formdata": [
						{
							"key": "user_id",
							"value": "175f4d02-fe49-4c44-b66f-2b6c9ee1fbae",
							"description": "请先创建用户再上传",
							"type": "text"
						},
						{
							"key": "file_url",
							"value": "",
							"type": "text"
						},
						{
							"key": "knowledge_base_id",
							"value": "xxx",
							"description": "可选值，上传到知识库的话需要填",
							"type": "text"
						},
						{
							"key": "mode",
							"value": "simple",
							"description": "非必填，可选模式为simple | normal。 不传默认是simple，会阻塞后返回状态。normal模式直接返回status。",
							"type": "text"
						}
					]
				},
				"url": {
					"raw": "http://120.46.208.202:8087/process",
					"protocol": "http",
					"host": [
						"120",
						"46",
						"208",
						"202"
					],
					"port": "8087",
					"path": [
						"process"
					]
				}
			},
			"response": [
				{
					"name": "【文件上传】【存文件到知识库】",
					"originalRequest": {
						"method": "POST",
						"header": [],
						"body": {
							"mode": "formdata",
							"formdata": [
								{
									"key": "user_id",
									"value": "xxxxx",
									"type": "text"
								},
								{
									"key": "file_url",
									"value": "http://1.tcp.cpolar.cn:21729/publicfiles/xxxx/default_file_space/f76ae7d3-db94-4fbd-ab2c-419eaec553b3/embedding_service -9030.py",
									"type": "text"
								},
								{
									"key": "knowledge_base_id",
									"value": "xxx",
									"description": "可选值，上传到知识库的话需要填",
									"type": "text"
								},
								{
									"key": "mode",
									"value": "normal",
									"description": "非必填，可选模式为simple | normal。 不传默认是simple，会阻塞后返回状态。normal模式直接返回status。",
									"type": "text"
								}
							]
						},
						"url": {
							"raw": "http://8.tcp.cpolar.cn:11195/process",
							"protocol": "http",
							"host": [
								"8",
								"tcp",
								"cpolar",
								"cn"
							],
							"port": "11195",
							"path": [
								"process"
							]
						}
					},
					"status": "OK",
					"code": 200,
					"_postman_previewlanguage": "json",
					"header": [
						{
							"key": "Connection",
							"value": "close"
						},
						{
							"key": "Content-Length",
							"value": "266"
						},
						{
							"key": "Content-Type",
							"value": "application/json"
						},
						{
							"key": "Date",
							"value": "Tue, 10 Jun 2025 09:20:14 GMT"
						},
						{
							"key": "Server",
							"value": "uvicorn"
						}
					],
					"cookie": [],
					"body": "{\n    \"status\": \"ok\",\n    \"message\": \"File processed successfully\",\n    \"data\": {\n        \"user_id\": \"xxxxx\",\n        \"file_url\": \"http://1.tcp.cpolar.cn:21729/publicfiles/xxxx/default_file_space/f76ae7d3-db94-4fbd-ab2c-419eaec553b3/embedding_service -9030.py\",\n        \"knowledge_base_id\": \"xxx\",\n        \"mode\": \"normal\"\n    }\n}"
				}
			]
		},
		{
			"name": "【文件上传】【删除文件】",
			"request": {
				"method": "POST",
				"header": [],
				"body": {
					"mode": "formdata",
					"formdata": [
						{
							"key": "user_id",
							"value": "9836c8af-3eb9-4739-b6fa-52ec6687141d",
							"type": "text"
						},
						{
							"key": "file_id",
							"value": "814ee39a-bbfd-490c-9195-c8dde3690576",
							"description": "请先创建",
							"type": "text"
						},
						{
							"key": "knowledge_base_id",
							"value": "xxx",
							"type": "text"
						}
					]
				},
				"url": {
					"raw": "http://120.46.208.202:8087/delete_file",
					"protocol": "http",
					"host": [
						"120",
						"46",
						"208",
						"202"
					],
					"port": "8087",
					"path": [
						"delete_file"
					]
				}
			},
			"response": []
		},
		{
			"name": "【知识图谱】【给知识库生成知识图谱】",
			"request": {
				"method": "POST",
				"header": [],
				"body": {
					"mode": "formdata",
					"formdata": [
						{
							"key": "mode",
							"value": "produce",
							"type": "text"
						},
						{
							"key": "user_id",
							"value": "75cc796b-8f74-41c2-9735-902f7ca1b735",
							"type": "text"
						},
						{
							"key": "knowledge_base_id",
							"value": "8434d1b8-fe1c-4261-8585-6538a2527d99",
							"type": "text"
						},
						{
							"key": "level",
							"value": "document",
							"type": "text"
						}
					]
				},
				"url": {
					"raw": "http://120.46.208.202:8087/graph/knowledge_base",
					"protocol": "http",
					"host": [
						"120",
						"46",
						"208",
						"202"
					],
					"port": "8087",
					"path": [
						"graph",
						"knowledge_base"
					]
				}
			},
			"response": [
				{
					"name": "New Request",
					"originalRequest": {
						"method": "POST",
						"header": [],
						"body": {
							"mode": "formdata",
							"formdata": [
								{
									"key": "mode",
									"value": "produce",
									"type": "text"
								},
								{
									"key": "user_id",
									"value": "75cc796b-8f74-41c2-9735-902f7ca1b735",
									"type": "text"
								},
								{
									"key": "knowledge_base_id",
									"value": "8434d1b8-fe1c-4261-8585-6538a2527d99",
									"type": "text"
								},
								{
									"key": "level",
									"value": "document",
									"type": "text"
								}
							]
						},
						"url": {
							"raw": "http://120.46.208.202:8087/graph/knowledge_base",
							"protocol": "http",
							"host": [
								"120",
								"46",
								"208",
								"202"
							],
							"port": "8087",
							"path": [
								"graph",
								"knowledge_base"
							]
						}
					},
					"status": "OK",
					"code": 200,
					"_postman_previewlanguage": "json",
					"header": [
						{
							"key": "Connection",
							"value": "close"
						},
						{
							"key": "Content-Length",
							"value": "127"
						},
						{
							"key": "Content-Type",
							"value": "application/json"
						},
						{
							"key": "Date",
							"value": "Sun, 22 Jun 2025 08:49:24 GMT"
						},
						{
							"key": "Server",
							"value": "uvicorn"
						}
					],
					"cookie": [],
					"body": "{\n    \"status\": \"ok\",\n    \"message\": \"Document graph produced successfully\",\n    \"data\": {\n        \"status\": \"ok\",\n        \"message\": \"Tags generated successfully\"\n    }\n}"
				}
			]
		},
		{
			"name": "【知识图谱】【获取知识库的知识图谱】",
			"request": {
				"method": "POST",
				"header": [],
				"body": {
					"mode": "formdata",
					"formdata": [
						{
							"key": "mode",
							"value": "get",
							"type": "text"
						},
						{
							"key": "user_id",
							"value": "75cc796b-8f74-41c2-9735-902f7ca1b735",
							"type": "text"
						},
						{
							"key": "knowledge_base_id",
							"value": "8434d1b8-fe1c-4261-8585-6538a2527d99",
							"type": "text"
						},
						{
							"key": "level",
							"value": "document",
							"type": "text"
						}
					]
				},
				"url": {
					"raw": "http://120.46.208.202:8087/graph/knowledge_base",
					"protocol": "http",
					"host": [
						"120",
						"46",
						"208",
						"202"
					],
					"port": "8087",
					"path": [
						"graph",
						"knowledge_base"
					]
				}
			},
			"response": [
				{
					"name": "【知识图谱】【获取知识库的知识图谱】",
					"originalRequest": {
						"method": "POST",
						"header": [],
						"body": {
							"mode": "formdata",
							"formdata": [
								{
									"key": "mode",
									"value": "get",
									"type": "text"
								},
								{
									"key": "user_id",
									"value": "75cc796b-8f74-41c2-9735-902f7ca1b735",
									"type": "text"
								},
								{
									"key": "knowledge_base_id",
									"value": "8434d1b8-fe1c-4261-8585-6538a2527d99",
									"type": "text"
								},
								{
									"key": "level",
									"value": "document",
									"type": "text"
								}
							]
						},
						"url": {
							"raw": "http://120.46.208.202:8087/graph/knowledge_base",
							"protocol": "http",
							"host": [
								"120",
								"46",
								"208",
								"202"
							],
							"port": "8087",
							"path": [
								"graph",
								"knowledge_base"
							]
						}
					},
					"status": "OK",
					"code": 200,
					"_postman_previewlanguage": "json",
					"header": [
						{
							"key": "Connection",
							"value": "close"
						},
						{
							"key": "Content-Length",
							"value": "1173"
						},
						{
							"key": "Content-Type",
							"value": "application/json"
						},
						{
							"key": "Date",
							"value": "Sun, 22 Jun 2025 08:50:01 GMT"
						},
						{
							"key": "Server",
							"value": "uvicorn"
						}
					],
					"cookie": [],
					"body": "{\n    \"status\": \"ok\",\n    \"message\": \"Document graph fetched successfully\",\n    \"data\": {\n        \"status\": \"ok\",\n        \"documents\": [\n            {\n                \"id\": \"5a29d543-3fdd-47b7-99cc-e5a366a08d08\",\n                \"name\": \"5a29d543-3fdd-47b7-99cc-e5a366a08d08.pdf\",\n                \"tags\": [\n                    \"AI模型应用\",\n                    \"数据处理与分析\",\n                    \"软件架构与技术\",\n                    \"数据安全与权限管理\",\n                    \"接口设计与集成\",\n                    \"政务数字化转型\"\n                ]\n            },\n            {\n                \"id\": \"5093fe8c-949f-441d-90e6-59102fdcf16b\",\n                \"name\": \"Document 5093fe8c-949f-441d-90e6-59102fdcf16b\",\n                \"tags\": [\n                    \"网页悬浮播放器\",\n                    \"API接口开发\",\n                    \"视频播放功能\",\n                    \"JS控制\",\n                    \"HTTPS配置\",\n                    \"开发环境\"\n                ]\n            },\n            {\n                \"id\": \"50785b91-50cc-4b57-90ce-6fbfe690e347\",\n                \"name\": \"50785b91-50cc-4b57-90ce-6fbfe690e347.pdf\",\n                \"tags\": [\n                    \"网页悬浮播放器\",\n                    \"API接口\",\n                    \"JS控制\",\n                    \"HTTPS对接\",\n                    \"鉴权机制\",\n                    \"开发指南\"\n                ]\n            },\n            {\n                \"id\": \"8f5bdfb0-99a9-497e-b359-9561d82ffa0f\",\n                \"name\": \"8f5bdfb0-99a9-497e-b359-9561d82ffa0f.pdf\",\n                \"tags\": [\n                    \"网页悬浮播放器\",\n                    \"开发接口\",\n                    \"JS控制\",\n                    \"HTTPS配置\",\n                    \"云台控制\",\n                    \"RESTful接口\"\n                ]\n            },\n            {\n                \"id\": \"bfda6167-d47e-48ed-b5e3-5307774cef70\",\n                \"name\": \"bfda6167-d47e-48ed-b5e3-5307774cef70.pdf\",\n                \"tags\": [\n                    \"网页悬浮播放器\",\n                    \"API接口开发\",\n                    \"JavaScript集成\",\n                    \"HTTPS配置\",\n                    \"视频播放控制\",\n                    \"云台控制\"\n                ]\n            }\n        ]\n    }\n}"
				}
			]
		}
	]
}